databased/__init__.py
databased/create_shell.py
databased/customshell.py
databased/databased.py
databased/dbparsers.py
databased/dbshell.py
databased/py.typed
databased-4.3.8.dist-info/METADATA
databased-4.3.8.dist-info/WHEEL
databased-4.3.8.dist-info/entry_points.txt
databased-4.3.8.dist-info/licenses/LICENSE.txt
databased-4.3.8.dist-info/RECORD
