Metadata-Version: 2.3
Name: databased
Version: 4.3.8
Summary: Wrapper for the standard library Sqlite3 module to make setting up and using a database quicker and easier.
Project-URL: Homepage, https://github.com/matt-manes/databased
Project-URL: Documentation, https://github.com/matt-manes/databased/tree/main/docs
Project-URL: Source code, https://github.com/matt-manes/databased/tree/main/src/databased
Author-email: Matt Manes <mattmanes@pm.me>
License-File: LICENSE.txt
Keywords: database,sqlite,sqlite3
Classifier: License :: OSI Approved :: MIT License
Classifier: Operating System :: OS Independent
Classifier: Programming Language :: Python :: 3
Requires-Python: <=3.12,>=3.10
Requires-Dist: argshell
Requires-Dist: griddle
Requires-Dist: loggi
Requires-Dist: noiftimer
Requires-Dist: pathier
Requires-Dist: printbuddies
Requires-Dist: rich
Requires-Dist: tabulate
